seissolxdmf/__init__.py
seissolxdmf/seissolxdmf.py
seissolxdmf-0.1.3.dist-info/LICENSE
seissolxdmf-0.1.3.dist-info/METADATA
seissolxdmf-0.1.3.dist-info/WHEEL
seissolxdmf-0.1.3.dist-info/top_level.txt
seissolxdmf-0.1.3.dist-info/RECORD
