Metadata-Version: 2.1
Name: seissolxdmf
Version: 0.1.3
Summary: A python reader for SeisSol xdmf output
Home-page: https://github.com/SeisSol/Visualization/seissolxdmf
Author: SeisSol Group
Classifier: Programming Language :: Python :: 3
Classifier: License :: OSI Approved :: BSD License
Classifier: Operating System :: OS Independent
Requires-Python: >=3.6
License-File: LICENSE
Requires-Dist: numpy
Requires-Dist: h5py
